aas_standard_parser/__init__.py
aas_standard_parser/aas_parser.py
aas_standard_parser/aid_parser.py
aas_standard_parser/aimc_parser.py
aas_standard_parser/collection_helpers.py
aas_standard_parser/reference_helpers.py
aas_standard_parser/submodel_json_parser.py
aas_standard_parser/submodel_parser.py
aas_standard_parser/utils.py
aas_standard_parser/version_check.py
aas_standard_parser/classes/aimc_parser_classes.py
aas_standard_parser/demo/demo_process.py
aas_standard_parser/demo/logging_handler.py
aas_standard_parser-0.3.2.dist-info/licenses/LICENSE
aas_standard_parser-0.3.2.dist-info/METADATA
aas_standard_parser-0.3.2.dist-info/WHEEL
aas_standard_parser-0.3.2.dist-info/top_level.txt
aas_standard_parser-0.3.2.dist-info/RECORD
