Metadata-Version: 2.4
Name: aas-standard-parser
Version: 0.3.2
Summary: Some auxiliary functions for parsing standard submodels
Author-email: Daniel Klein <daniel.klein@em.ag>
License: MIT License
Project-URL: Homepage, https://github.com/fluid40/aas-standard-parser
Requires-Python: >=3.11
License-File: LICENSE
Requires-Dist: basyx-python-sdk>=2.0.0
Requires-Dist: python-json-logger>=4.0.0
Requires-Dist: requests>=2.32.5
Dynamic: license-file
